[
    {
        "title": "NLW 5 Flutter",
        "image": "blocks",
        "questionAnswereds": 1,
        "level": "facil",
        "questions":[
            {
                "title" : "Pergunta teste 1",
                "awnsers": [
                    {"title" : "teste 1"},
                    {"title" : "teste 2"},
                    {"title" : "teste 3"},
                    {"title" : "teste 4" , "isRight": true}

                ]
            },
            {
                "title" : "Pergunta teste",
                "awnsers": [
                    {"title" : "teste 1"},
                    {"title" : "teste 2"},
                    {"title" : "teste 3"},
                    {"title" : "teste 4" , "isRight": true}

                ]
            },
            {
                "title" : "Pergunta teste",
                "awnsers": [
                    {"title" : "teste 1"},
                    {"title" : "teste 2"},
                    {"title" : "teste 3"},
                    {"title" : "teste 4" , "isRight": true}

                ]
            }
        ]
    }
]